melodist/__init__.py
melodist/__version__.py
melodist/cascade.py
melodist/data_io.py
melodist/humidity.py
melodist/precipitation.py
melodist/radiation.py
melodist/station.py
melodist/stationstatistics.py
melodist/temperature.py
melodist/wind.py
melodist/util/__init__.py
melodist/util/bunch.py
melodist/util/util.py
melodist-0.1.6.dist-info/Licence_GPLv3.txt
melodist-0.1.6.dist-info/METADATA
melodist-0.1.6.dist-info/WHEEL
melodist-0.1.6.dist-info/top_level.txt
melodist-0.1.6.dist-info/RECORD
