Metadata-Version: 2.1
Name: melodist
Version: 0.1.6
Summary: MELODIST: MEteoroLOgical observation time series DISaggregation Tool
Home-page: https://github.com/kristianfoerster/melodist
Author: Kristian Förster, Florian Hanzer, Benjamin Winter, Thomas Marke, Siling Chen
Author-email: kristian.foerster@hswt.de
License: GPLv3
Platform: any
Classifier: Development Status :: 4 - Beta
Classifier: Intended Audience :: Science/Research
Classifier: Topic :: Scientific/Engineering :: Atmospheric Science
Classifier: License :: OSI Approved :: GNU General Public License v3 (GPLv3)
Classifier: Programming Language :: Python :: 3
Classifier: Programming Language :: Python :: 3.4
Classifier: Programming Language :: Python :: 3.5
Classifier: Programming Language :: Python :: 3.6
Classifier: Programming Language :: Python :: 3.7
Classifier: Programming Language :: Python :: 3.8
Classifier: Programming Language :: Python :: 3.9
Classifier: Programming Language :: Python :: 3.10
Classifier: Programming Language :: Python :: 3.11
Classifier: Programming Language :: Python :: 3.12
Requires-Python: >=3.8
License-File: Licence_GPLv3.txt
Requires-Dist: numpy
Requires-Dist: pandas
Requires-Dist: scipy
Provides-Extra: test
Requires-Dist: pytest ; extra == 'test'
